[
    {
        "key": "dbln",
        "value": "%7B%2261579403792759%22%3A%22GLesUy7H%22%7D",
        "domain": "facebook.com",
        "path": "/login/device-based/",
        "hostOnly": false,
        "creation": "2026-03-18T15:59:05.311Z",
        "lastAccessed": "2026-03-18T15:59:05.313Z"
    },
    {
        "key": "datr",
        "value": "QWe6aVYgMHw8z4lm1XUcNbDT",
        "domain": "facebook.com",
        "path": "/",
        "hostOnly": false,
        "creation": "2026-03-18T15:59:05.313Z",
        "lastAccessed": "2026-03-18T15:59:05.313Z"
    },
    {
        "key": "dpr",
        "value": "2",
        "domain": "facebook.com",
        "path": "/",
        "hostOnly": false,
        "creation": "2026-03-18T15:59:05.313Z",
        "lastAccessed": "2026-03-18T15:59:05.313Z"
    },
    {
        "key": "sb",
        "value": "DGi6aZH1zTeN-28y2lZBNRT1",
        "domain": "facebook.com",
        "path": "/",
        "hostOnly": false,
        "creation": "2026-03-18T15:59:05.313Z",
        "lastAccessed": "2026-03-18T15:59:05.313Z"
    },
    {
        "key": "c_user",
        "value": "61579403792759",
        "domain": "facebook.com",
        "path": "/",
        "hostOnly": false,
        "creation": "2026-03-18T15:59:05.313Z",
        "lastAccessed": "2026-03-18T15:59:05.313Z"
    },
    {
        "key": "xs",
        "value": "42%3ATYGWXBDavXHFWg%3A2%3A1773829028%3A-1%3A-1",
        "domain": "facebook.com",
        "path": "/",
        "hostOnly": false,
        "creation": "2026-03-18T15:59:05.313Z",
        "lastAccessed": "2026-03-18T15:59:05.313Z"
    },
    {
        "key": "locale",
        "value": "en_US",
        "domain": "facebook.com",
        "path": "/",
        "hostOnly": false,
        "creation": "2026-03-18T15:59:05.313Z",
        "lastAccessed": "2026-03-18T15:59:05.313Z"
    },
    {
        "key": "pas",
        "value": "61579403792759%3AGJOcowQAfl",
        "domain": "facebook.com",
        "path": "/",
        "hostOnly": false,
        "creation": "2026-03-18T15:59:05.313Z",
        "lastAccessed": "2026-03-18T15:59:05.313Z"
    },
    {
        "key": "ps_l",
        "value": "1",
        "domain": "facebook.com",
        "path": "/",
        "hostOnly": false,
        "creation": "2026-03-18T15:59:05.313Z",
        "lastAccessed": "2026-03-18T15:59:05.313Z"
    },
    {
        "key": "ps_n",
        "value": "1",
        "domain": "facebook.com",
        "path": "/",
        "hostOnly": false,
        "creation": "2026-03-18T15:59:05.314Z",
        "lastAccessed": "2026-03-18T15:59:05.314Z"
    },
    {
        "key": "vpd",
        "value": "v1%3B618x360x2",
        "domain": "facebook.com",
        "path": "/",
        "hostOnly": false,
        "creation": "2026-03-18T15:59:05.314Z",
        "lastAccessed": "2026-03-18T15:59:05.314Z"
    },
    {
        "key": "fr",
        "value": "0fbU87yWABLiGkVIW.AWeclA68XoZd4D6bu9Gi9-oe4R8p_OUfbzRkQIRIF_VR5fVoLTY.BpumdC..AAA.0.0.Bpussj.AWeUp2Rkjv55mZ1AauxoKJu9Z7A",
        "domain": "facebook.com",
        "path": "/",
        "hostOnly": false,
        "creation": "2026-03-18T15:59:05.314Z",
        "lastAccessed": "2026-03-18T15:59:05.314Z"
    },
    {
        "key": "wl_cbv",
        "value": "v2%3Bclient_version%3A3113%3Btimestamp%3A1773849379",
        "domain": "facebook.com",
        "path": "/",
        "hostOnly": false,
        "creation": "2026-03-18T15:59:05.314Z",
        "lastAccessed": "2026-03-18T15:59:05.314Z"
    },
    {
        "key": "fbl_st",
        "value": "100416047%3BT%3A29564156",
        "domain": "facebook.com",
        "path": "/",
        "hostOnly": false,
        "creation": "2026-03-18T15:59:05.314Z",
        "lastAccessed": "2026-03-18T15:59:05.314Z"
    }
        ]
